prism_engines/__init__.py
prism_engines/data.py
prism_engines/runner.py
prism_engines/engines/__init__.py
prism_engines/engines/base.py
prism_engines/engines/correlation.py
prism_engines/engines/hurst.py
prism_engines/engines/pca.py
prism_engines-0.1.0.dist-info/licenses/LICENSE
prism_engines-0.1.0.dist-info/METADATA
prism_engines-0.1.0.dist-info/WHEEL
prism_engines-0.1.0.dist-info/top_level.txt
prism_engines-0.1.0.dist-info/RECORD
