Metadata-Version: 2.4
Name: prism-engines
Version: 0.1.0
Summary: Geometric analysis engines for time series data
Author: PRISM Research
License: MIT
Project-URL: Homepage, https://github.com/rudder-research/prism-engines
Project-URL: Documentation, https://github.com/rudder-research/prism-engines#readme
Project-URL: Repository, https://github.com/rudder-research/prism-engines
Keywords: time-series,analysis,pca,correlation,geometry
Classifier: Development Status :: 3 - Alpha
Classifier: Intended Audience :: Science/Research
Classifier: License :: OSI Approved :: MIT License
Classifier: Programming Language :: Python :: 3
Classifier: Programming Language :: Python :: 3.9
Classifier: Programming Language :: Python :: 3.10
Classifier: Programming Language :: Python :: 3.11
Classifier: Programming Language :: Python :: 3.12
Classifier: Topic :: Scientific/Engineering
Requires-Python: >=3.9
License-File: LICENSE
Requires-Dist: numpy>=1.20
Requires-Dist: pandas>=1.3
Provides-Extra: plot
Requires-Dist: matplotlib>=3.5; extra == "plot"
Provides-Extra: dev
Requires-Dist: pytest>=7.0; extra == "dev"
Requires-Dist: matplotlib>=3.5; extra == "dev"
Provides-Extra: all
Requires-Dist: matplotlib>=3.5; extra == "all"
Dynamic: license-file
